odoo/addons/sale_order_line_description/README.rst
odoo/addons/sale_order_line_description/__init__.py
odoo/addons/sale_order_line_description/__manifest__.py
odoo/addons/sale_order_line_description/i18n/ca.po
odoo/addons/sale_order_line_description/i18n/de.po
odoo/addons/sale_order_line_description/i18n/es.po
odoo/addons/sale_order_line_description/i18n/es_VE.po
odoo/addons/sale_order_line_description/i18n/fr.po
odoo/addons/sale_order_line_description/i18n/hr.po
odoo/addons/sale_order_line_description/i18n/it.po
odoo/addons/sale_order_line_description/i18n/nl_NL.po
odoo/addons/sale_order_line_description/i18n/pt_BR.po
odoo/addons/sale_order_line_description/i18n/ro.po
odoo/addons/sale_order_line_description/i18n/sale_order_line_description.pot
odoo/addons/sale_order_line_description/i18n/sl.po
odoo/addons/sale_order_line_description/i18n/tr.po
odoo/addons/sale_order_line_description/i18n/tr_TR.po
odoo/addons/sale_order_line_description/i18n/zh_CN.po
odoo/addons/sale_order_line_description/models/__init__.py
odoo/addons/sale_order_line_description/models/res_config_settings.py
odoo/addons/sale_order_line_description/models/sale_order_line.py
odoo/addons/sale_order_line_description/readme/CONFIGURE.rst
odoo/addons/sale_order_line_description/readme/CONTRIBUTORS.rst
odoo/addons/sale_order_line_description/readme/DESCRIPTION.rst
odoo/addons/sale_order_line_description/readme/USAGE.rst
odoo/addons/sale_order_line_description/security/sale_security.xml
odoo/addons/sale_order_line_description/static/description/icon.png
odoo/addons/sale_order_line_description/static/description/index.html
odoo/addons/sale_order_line_description/tests/__init__.py
odoo/addons/sale_order_line_description/tests/test_sale.py
odoo/addons/sale_order_line_description/views/res_config_settings_views.xml
odoo13_addon_sale_order_line_description-13.0.1.0.1.dev8.dist-info/METADATA
odoo13_addon_sale_order_line_description-13.0.1.0.1.dev8.dist-info/WHEEL
odoo13_addon_sale_order_line_description-13.0.1.0.1.dev8.dist-info/top_level.txt
odoo13_addon_sale_order_line_description-13.0.1.0.1.dev8.dist-info/RECORD
